{
  "_note": "Auto-updated from TrackAIPAC + RLC + FEC. Manual entries preserved.",
  "_last_scraped": "2026-04-15T17:14:51.828776+00:00",
  "challengers": [
    {
      "name": "Andy Biggs",
      "state": "",
      "district": null,
      "party": "R",
      "chamber": "house",
      "antiArms": true,
      "antiArmsLevel": "soft",
      "ps": "UPCOMING",
      "primaryDate": "",
      "website": "",
      "source": "rlc_endorsed",
      "note": "Endorsed by Republican Liberty Caucus for House Speaker\" >",
      "opponent": "",
      "incumbentParty": ""
    },
    {
      "name": "Paul Rojas",
      "state": "",
      "district": null,
      "party": "R",
      "chamber": "house",
      "antiArms": true,
      "antiArmsLevel": "soft",
      "ps": "UPCOMING",
      "primaryDate": "",
      "website": "",
      "source": "rlc_endorsed",
      "note": "Endorsed by Republican Liberty Caucus for TX CD-21\" >",
      "opponent": "",
      "incumbentParty": ""
    },
    {
      "name": "Robb Ryerse",
      "state": "AR",
      "district": 3,
      "party": "D",
      "chamber": "house",
      "antiArms": true,
      "ps": "GENERAL",
      "primaryDate": "2026-11-03",
      "website": "https://www.robbforcongress.com/",
      "source": "manual+trackaipac",
      "note": "Endorsed by TrackAIPAC / Citizens Against AIPAC Corruption. Rejects AIPAC contributions.",
      "opponent": "",
      "incumbentParty": ""
    },
    {
      "name": "Kai Newkirk",
      "state": "AZ",
      "district": 4,
      "party": "D",
      "chamber": "house",
      "antiArms": true,
      "antiArmsLevel": "yes",
      "ps": "UPCOMING",
      "primaryDate": "2026-08-04",
      "website": "https://www.kaiforaz.com/",
      "source": "trackaipac",
      "note": "Endorsed by Citizens Against AIPAC Corruption.",
      "opponent": "",
      "incumbentParty": ""
    },
    {
      "name": "Angela Gonzales-Torres",
      "state": "CA",
      "district": 34,
      "party": "D",
      "chamber": "house",
      "antiArms": true,
      "ps": "UPCOMING",
      "primaryDate": "2026-06-02",
      "website": "https://www.angela4congress.com/",
      "source": "manual+trackaipac",
      "note": "Endorsed by TrackAIPAC / Citizens Against AIPAC Corruption. Rejects AIPAC contributions.",
      "opponent": "",
      "incumbentParty": ""
    },
    {
      "name": "Ang\u00e9lica Due\u00f1as",
      "state": "CA",
      "district": 29,
      "party": "D",
      "chamber": "house",
      "antiArms": true,
      "antiArmsLevel": "yes",
      "ps": "UPCOMING",
      "primaryDate": "2026-06-02",
      "website": "https://angelica4congress.com/",
      "source": "trackaipac",
      "note": "Endorsed by Citizens Against AIPAC Corruption.",
      "opponent": "",
      "incumbentParty": ""
    },
    {
      "name": "Audrey Denney",
      "state": "CA",
      "district": 1,
      "party": "D",
      "chamber": "house",
      "antiArms": true,
      "antiArmsLevel": "yes",
      "ps": "UPCOMING",
      "primaryDate": "2026-06-02",
      "website": "https://audreyforcongress.com/",
      "source": "trackaipac",
      "note": "Endorsed by Citizens Against AIPAC Corruption.",
      "opponent": "",
      "incumbentParty": ""
    },
    {
      "name": "Chris Ahuja",
      "state": "CA",
      "district": 32,
      "party": "D",
      "chamber": "house",
      "antiArms": true,
      "ps": "UPCOMING",
      "primaryDate": "2026-06-02",
      "website": "https://www.chrisahuja.com/",
      "source": "manual+trackaipac",
      "note": "Endorsed by TrackAIPAC / Citizens Against AIPAC Corruption. Rejects AIPAC contributions.",
      "opponent": "",
      "incumbentParty": ""
    },
    {
      "name": "Chris Bennett",
      "state": "CA",
      "district": 3,
      "party": "D",
      "chamber": "house",
      "antiArms": true,
      "ps": "UPCOMING",
      "primaryDate": "2026-06-02",
      "website": "https://bennettforca.com/",
      "source": "manual+trackaipac",
      "note": "Endorsed by TrackAIPAC / Citizens Against AIPAC Corruption. Rejects AIPAC contributions.",
      "opponent": "",
      "incumbentParty": ""
    },
    {
      "name": "Mai Vang",
      "state": "CA",
      "district": 7,
      "party": "D",
      "chamber": "house",
      "antiArms": true,
      "ps": "UPCOMING",
      "primaryDate": "2026-06-02",
      "website": "https://www.maiforus.com/",
      "source": "manual+trackaipac",
      "note": "Endorsed by TrackAIPAC / Citizens Against AIPAC Corruption. Rejects AIPAC contributions.",
      "opponent": "",
      "incumbentParty": ""
    },
    {
      "name": "Marianne Shamma",
      "state": "CA",
      "district": 36,
      "party": "D",
      "chamber": "house",
      "antiArms": true,
      "antiArmsLevel": "yes",
      "ps": "UPCOMING",
      "primaryDate": "2026-06-02",
      "website": "https://www.mariannehumanityfirst.com/",
      "source": "trackaipac",
      "note": "Endorsed by Citizens Against AIPAC Corruption.",
      "opponent": "",
      "incumbentParty": ""
    },
    {
      "name": "Randy Villegas",
      "state": "CA",
      "district": 22,
      "party": "D",
      "chamber": "house",
      "antiArms": true,
      "ps": "UPCOMING",
      "primaryDate": "2026-06-02",
      "website": "https://www.villegasforcongress.com/",
      "source": "manual+trackaipac",
      "note": "Endorsed by TrackAIPAC / Citizens Against AIPAC Corruption. Rejects AIPAC contributions.",
      "opponent": "",
      "incumbentParty": ""
    },
    {
      "name": "Rose Penelope Yee",
      "state": "CA",
      "district": 2,
      "party": "D",
      "chamber": "house",
      "antiArms": true,
      "antiArmsLevel": "yes",
      "ps": "UPCOMING",
      "primaryDate": "2026-06-02",
      "website": "https://roseforcongress.com/",
      "source": "trackaipac",
      "note": "Endorsed by Citizens Against AIPAC Corruption.",
      "opponent": "",
      "incumbentParty": ""
    },
    {
      "name": "Saikat Chakrabarti",
      "state": "CA",
      "district": 11,
      "party": "D",
      "chamber": "house",
      "antiArms": true,
      "ps": "UPCOMING",
      "primaryDate": "2026-06-02",
      "website": "https://www.saikat.us/",
      "source": "manual+trackaipac",
      "note": "Endorsed by TrackAIPAC / Citizens Against AIPAC Corruption. Rejects AIPAC contributions.",
      "opponent": "",
      "incumbentParty": ""
    },
    {
      "name": "Sean Dougherty",
      "state": "CA",
      "district": 19,
      "party": "D",
      "chamber": "house",
      "antiArms": true,
      "antiArmsLevel": "yes",
      "ps": "UPCOMING",
      "primaryDate": "2026-06-02",
      "website": "https://seanforcongress.org/",
      "source": "trackaipac",
      "note": "Endorsed by Citizens Against AIPAC Corruption.",
      "opponent": "",
      "incumbentParty": ""
    },
    {
      "name": "Sparky Mitra",
      "state": "CA",
      "district": 50,
      "party": "D",
      "chamber": "house",
      "antiArms": true,
      "antiArmsLevel": "yes",
      "ps": "UPCOMING",
      "primaryDate": "2026-06-02",
      "website": "https://www.sparkymitra.com/",
      "source": "trackaipac",
      "note": "Endorsed by Citizens Against AIPAC Corruption.",
      "opponent": "",
      "incumbentParty": ""
    },
    {
      "name": "John Padora",
      "state": "CO",
      "district": 4,
      "party": "D",
      "chamber": "house",
      "antiArms": true,
      "ps": "UPCOMING",
      "primaryDate": "2026-06-30",
      "website": "https://www.padoraforcongress.com/",
      "source": "manual+trackaipac",
      "note": "Endorsed by TrackAIPAC / Citizens Against AIPAC Corruption. Rejects AIPAC contributions.",
      "opponent": "",
      "incumbentParty": ""
    },
    {
      "name": "Melat Kiros",
      "state": "CO",
      "district": 1,
      "party": "D",
      "chamber": "house",
      "antiArms": true,
      "ps": "UPCOMING",
      "primaryDate": "2026-06-30",
      "website": "https://www.kirosforco.com/",
      "source": "manual+trackaipac",
      "note": "Endorsed by TrackAIPAC / Citizens Against AIPAC Corruption. Rejects AIPAC contributions.",
      "opponent": "",
      "incumbentParty": ""
    },
    {
      "name": "Andrew Rice",
      "state": "CT",
      "district": 3,
      "party": "D",
      "chamber": "house",
      "antiArms": true,
      "ps": "UPCOMING",
      "primaryDate": "2026-08-11",
      "website": "https://www.riceforct.com/",
      "source": "manual+trackaipac",
      "note": "Endorsed by TrackAIPAC / Citizens Against AIPAC Corruption. Rejects AIPAC contributions.",
      "opponent": "",
      "incumbentParty": ""
    },
    {
      "name": "Bernard Taylor",
      "state": "FL",
      "district": 21,
      "party": "D",
      "chamber": "house",
      "antiArms": true,
      "ps": "UPCOMING",
      "primaryDate": "2026-08-18",
      "website": "https://www.bernardtaylorforcongress.org/",
      "source": "manual+trackaipac",
      "note": "Endorsed by TrackAIPAC / Citizens Against AIPAC Corruption. Rejects AIPAC contributions.",
      "opponent": "",
      "incumbentParty": ""
    },
    {
      "name": "Elijah Manley",
      "state": "FL",
      "district": 20,
      "party": "D",
      "chamber": "house",
      "antiArms": true,
      "ps": "UPCOMING",
      "primaryDate": "2026-08-18",
      "website": "https://www.elijahmanley.com/",
      "source": "manual+trackaipac",
      "note": "Endorsed by TrackAIPAC / Citizens Against AIPAC Corruption. Rejects AIPAC contributions.",
      "opponent": "",
      "incumbentParty": ""
    },
    {
      "name": "John Mills",
      "state": "FL",
      "district": 1,
      "party": "R",
      "chamber": "house",
      "antiArms": true,
      "antiArmsLevel": "soft",
      "ps": "UPCOMING",
      "primaryDate": "",
      "website": "",
      "source": "rlc_endorsed",
      "note": "Endorsed by Republican Liberty Caucus for Florida&#8217;s 1st Congressional District\" >",
      "opponent": "",
      "incumbentParty": ""
    },
    {
      "name": "Kat Cammack",
      "state": "FL",
      "district": 3,
      "party": "R",
      "chamber": "house",
      "antiArms": true,
      "antiArmsLevel": "soft",
      "ps": "UPCOMING",
      "primaryDate": "",
      "website": "",
      "source": "rlc_endorsed",
      "note": "Endorsed by Republican Liberty Caucus for Florida&#8217;s 3rd Congressional District\" >",
      "opponent": "",
      "incumbentParty": ""
    },
    {
      "name": "Marialana Kinter",
      "state": "FL",
      "district": 7,
      "party": "D",
      "chamber": "house",
      "antiArms": true,
      "ps": "UPCOMING",
      "primaryDate": "2026-08-18",
      "website": "https://www.kinterforcongress.com/",
      "source": "manual+trackaipac",
      "note": "Endorsed by TrackAIPAC / Citizens Against AIPAC Corruption. Rejects AIPAC contributions.",
      "opponent": "",
      "incumbentParty": ""
    },
    {
      "name": "Oliver Larkin",
      "state": "FL",
      "district": 23,
      "party": "D",
      "chamber": "house",
      "antiArms": true,
      "ps": "UPCOMING",
      "primaryDate": "2026-08-18",
      "website": "https://www.oliverforcongress.com/",
      "source": "manual+trackaipac",
      "note": "Endorsed by TrackAIPAC / Citizens Against AIPAC Corruption. Rejects AIPAC contributions.",
      "opponent": "",
      "incumbentParty": ""
    },
    {
      "name": "Willie J Montague",
      "state": "FL",
      "district": 10,
      "party": "R",
      "chamber": "house",
      "antiArms": true,
      "antiArmsLevel": "soft",
      "ps": "UPCOMING",
      "primaryDate": "",
      "website": "",
      "source": "rlc_endorsed",
      "note": "Endorsed by Republican Liberty Caucus for Florida&#8217;s 10th Congressional District\" >",
      "opponent": "",
      "incumbentParty": ""
    },
    {
      "name": "Case Norton",
      "state": "GA",
      "district": 7,
      "party": "D",
      "chamber": "house",
      "antiArms": true,
      "antiArmsLevel": "yes",
      "ps": "UPCOMING",
      "primaryDate": "2026-05-19",
      "website": "https://www.case4congress.com/",
      "source": "trackaipac",
      "note": "Endorsed by Citizens Against AIPAC Corruption.",
      "opponent": "",
      "incumbentParty": ""
    },
    {
      "name": "Everton Blair",
      "state": "GA",
      "district": 13,
      "party": "D",
      "chamber": "house",
      "antiArms": true,
      "antiArmsLevel": "yes",
      "ps": "UPCOMING",
      "primaryDate": "2026-05-19",
      "website": "https://www.evertonblair.com/",
      "source": "trackaipac",
      "note": "Endorsed by Citizens Against AIPAC Corruption.",
      "opponent": "",
      "incumbentParty": ""
    },
    {
      "name": "Summer Shelton",
      "state": "GA",
      "district": 6,
      "party": "D",
      "chamber": "house",
      "note": "Progressive challenger on full arms embargo vs. Rep. Lucy McBath.",
      "primaryDate": "2026-05-19",
      "ps": "UPCOMING",
      "opponent": "Lucy McBath (incumbent)",
      "incumbentParty": "D"
    },
    {
      "name": "Travis Terrell",
      "state": "IA",
      "district": 1,
      "party": "D",
      "chamber": "house",
      "antiArms": true,
      "antiArmsLevel": "yes",
      "ps": "UPCOMING",
      "primaryDate": "2026-06-02",
      "website": "https://terrellforcongress.com/",
      "source": "trackaipac",
      "note": "Endorsed by Citizens Against AIPAC Corruption.",
      "opponent": "",
      "incumbentParty": ""
    },
    {
      "name": "Anabel Mendoza",
      "state": "IL",
      "district": 7,
      "party": "D",
      "chamber": "house",
      "antiArms": true,
      "ps": "UPCOMING",
      "primaryDate": "2026-03-17",
      "website": "https://www.anabelforcongress.com/",
      "source": "manual+trackaipac",
      "note": "Endorsed by TrackAIPAC / Citizens Against AIPAC Corruption. Rejects AIPAC contributions.",
      "opponent": "",
      "incumbentParty": ""
    },
    {
      "name": "Bushra Amiwala",
      "state": "IL",
      "district": 9,
      "party": "D",
      "chamber": "house",
      "antiArms": true,
      "ps": "UPCOMING",
      "primaryDate": "2026-03-17",
      "website": "https://www.bushraforcongress.com/",
      "source": "manual+trackaipac",
      "note": "Endorsed by TrackAIPAC / Citizens Against AIPAC Corruption. Rejects AIPAC contributions.",
      "opponent": "",
      "incumbentParty": "",
      "fec_id": "H6IL09236"
    },
    {
      "name": "Daniel Biss",
      "state": "IL",
      "district": 9,
      "party": "D",
      "chamber": "house",
      "note": "Evanston mayor; endorsed by Schakowsky; supports ceasefire and weapons pause to Israel. Running for same IL-9 open seat (3-way with Abughazaleh and Fine). Leads in early polls at ~24%.",
      "primaryDate": "2026-03-17",
      "ps": "UPCOMING",
      "opponent": "Open seat (Schakowsky retiring)",
      "incumbentParty": "D"
    },
    {
      "name": "Dylan Blaha",
      "state": "IL",
      "district": 13,
      "party": "D",
      "chamber": "house",
      "antiArms": true,
      "ps": "UPCOMING",
      "primaryDate": "2026-03-17",
      "website": "https://www.dylanforillinois.com/",
      "source": "manual+trackaipac",
      "note": "Endorsed by TrackAIPAC / Citizens Against AIPAC Corruption. Rejects AIPAC contributions.",
      "opponent": "",
      "incumbentParty": ""
    },
    {
      "name": "Joey Ruzevich",
      "state": "IL",
      "district": 6,
      "party": "D",
      "chamber": "house",
      "antiArms": true,
      "ps": "UPCOMING",
      "primaryDate": "",
      "website": "https://www.joey4congress.com/",
      "source": "manual+trackaipac",
      "note": "Endorsed by TrackAIPAC / Citizens Against AIPAC Corruption. Rejects AIPAC contributions.",
      "opponent": "",
      "incumbentParty": ""
    },
    {
      "name": "Junaid Ahmed",
      "state": "IL",
      "district": 8,
      "party": "D",
      "chamber": "house",
      "note": "Arms embargo advocate for open seat. Endorsed by Khanna, Ramirez, Jayapal. Led fundraising at $838K.",
      "primaryDate": "2026-06-02",
      "ps": "UPCOMING",
      "opponent": "Open seat",
      "incumbentParty": "D",
      "website": "https://junaidforus.com/",
      "source": "manual+trackaipac",
      "antiArms": true,
      "fec_id": "H2IL08146"
    },
    {
      "name": "Kat Abughazaleh",
      "state": "IL",
      "district": 9,
      "party": "D",
      "chamber": "house",
      "note": "Journalist and digital creator; grandchild of Nakba survivors; endorsed by CAIR Action and Justice Democrats. Calls for full arms embargo. Running for Schakowsky's open IL-9 seat (3-way with Biss and Fine).",
      "primaryDate": "2026-03-17",
      "ps": "UPCOMING",
      "opponent": "Open seat (Schakowsky retiring)",
      "incumbentParty": "D",
      "website": "https://www.katforillinois.com/",
      "source": "manual+trackaipac",
      "antiArms": true
    },
    {
      "name": "Kina Collins",
      "state": "IL",
      "district": 7,
      "party": "D",
      "chamber": "house",
      "antiArms": true,
      "ps": "UPCOMING",
      "primaryDate": "2026-03-17",
      "website": "https://www.kinacollinsil.com/",
      "source": "manual+trackaipac",
      "note": "Endorsed by TrackAIPAC / Citizens Against AIPAC Corruption. Rejects AIPAC contributions.",
      "opponent": "",
      "incumbentParty": ""
    },
    {
      "name": "Matt Conroy",
      "state": "IL",
      "district": 5,
      "party": "D",
      "chamber": "house",
      "antiArms": true,
      "ps": "UPCOMING",
      "primaryDate": "2026-03-17",
      "website": "https://www.mattconroyforcongress.com/",
      "source": "manual+trackaipac",
      "note": "Endorsed by TrackAIPAC / Citizens Against AIPAC Corruption. Rejects AIPAC contributions.",
      "opponent": "",
      "incumbentParty": ""
    },
    {
      "name": "Mike Simmons",
      "state": "IL",
      "district": 9,
      "party": "D",
      "chamber": "house",
      "antiArms": true,
      "ps": "UPCOMING",
      "primaryDate": "2026-03-17",
      "website": "https://www.mikesimmons.org/",
      "source": "manual+trackaipac",
      "note": "Endorsed by TrackAIPAC / Citizens Against AIPAC Corruption. Rejects AIPAC contributions.",
      "opponent": "",
      "incumbentParty": ""
    },
    {
      "name": "Morgan Coghill",
      "state": "IL",
      "district": 10,
      "party": "D",
      "chamber": "house",
      "antiArms": true,
      "ps": "UPCOMING",
      "primaryDate": "2026-03-17",
      "website": "https://www.coghillforcongress.com/",
      "source": "manual+trackaipac",
      "note": "Endorsed by TrackAIPAC / Citizens Against AIPAC Corruption. Rejects AIPAC contributions.",
      "opponent": "",
      "incumbentParty": ""
    },
    {
      "name": "Paul Nolley",
      "state": "IL",
      "district": 16,
      "party": "D",
      "chamber": "house",
      "antiArms": true,
      "ps": "UPCOMING",
      "primaryDate": "2026-03-17",
      "website": "https://www.nolleyforcongress.com/",
      "source": "manual+trackaipac",
      "note": "Endorsed by TrackAIPAC / Citizens Against AIPAC Corruption. Rejects AIPAC contributions.",
      "opponent": "",
      "incumbentParty": ""
    },
    {
      "name": "Reed Showalter",
      "state": "IL",
      "district": 7,
      "party": "D",
      "chamber": "house",
      "antiArms": true,
      "ps": "UPCOMING",
      "primaryDate": "2026-03-17",
      "website": "https://www.reed4congress.com/",
      "source": "manual+trackaipac",
      "note": "Endorsed by TrackAIPAC / Citizens Against AIPAC Corruption. Rejects AIPAC contributions.",
      "opponent": "",
      "incumbentParty": ""
    },
    {
      "name": "Robert Peters",
      "state": "IL",
      "district": 2,
      "party": "D",
      "chamber": "house",
      "antiArms": true,
      "ps": "UPCOMING",
      "primaryDate": "2026-03-17",
      "website": "https://www.robertpetersforcongress.com/",
      "source": "manual+trackaipac",
      "note": "Endorsed by TrackAIPAC / Citizens Against AIPAC Corruption. Rejects AIPAC contributions.",
      "opponent": "",
      "incumbentParty": ""
    },
    {
      "name": "Jackson Franklin",
      "state": "IN",
      "district": 5,
      "party": "D",
      "chamber": "house",
      "antiArms": true,
      "ps": "UPCOMING",
      "primaryDate": "2026-05-05",
      "website": "https://jacksonfranklinforcongress.com/",
      "source": "manual+trackaipac",
      "note": "Endorsed by TrackAIPAC / Citizens Against AIPAC Corruption. Rejects AIPAC contributions.",
      "opponent": "",
      "incumbentParty": ""
    },
    {
      "name": "Congressman Thomas Massie",
      "state": "KY",
      "district": 4,
      "party": "R",
      "chamber": "house",
      "antiArms": true,
      "antiArmsLevel": "soft",
      "ps": "UPCOMING",
      "primaryDate": "",
      "website": "",
      "source": "rlc_endorsed",
      "note": "Endorsed by Republican Liberty Caucus for Kentucky\u2019s 4th Congressional District",
      "opponent": "",
      "incumbentParty": ""
    },
    {
      "name": "William Compton",
      "state": "KY",
      "district": 2,
      "party": "D",
      "chamber": "house",
      "antiArms": true,
      "antiArmsLevel": "yes",
      "ps": "UPCOMING",
      "primaryDate": "2026-05-19",
      "website": "https://secure.actblue.com/donate/william-rejects-aipac?refcode=website-endorsement",
      "source": "trackaipac",
      "note": "Endorsed by Citizens Against AIPAC Corruption.",
      "opponent": "",
      "incumbentParty": ""
    },
    {
      "name": "Jack Schlossberg",
      "state": "MA",
      "district": null,
      "party": "D",
      "chamber": "senate",
      "note": "Running for MA Senate 2026. Pro-Palestinian lean; opposes offensive arms transfers.",
      "primaryDate": "2026-09-15",
      "ps": "UPCOMING",
      "opponent": "Open seat",
      "incumbentParty": "D"
    },
    {
      "name": "Jeromie Whalen",
      "state": "MA",
      "district": 1,
      "party": "D",
      "chamber": "house",
      "antiArms": true,
      "ps": "UPCOMING",
      "primaryDate": "2026-09-01",
      "website": "https://www.whalenforcongressma.com/",
      "source": "manual+trackaipac",
      "note": "Endorsed by TrackAIPAC / Citizens Against AIPAC Corruption. Rejects AIPAC contributions.",
      "opponent": "",
      "incumbentParty": ""
    },
    {
      "name": "Ethan Wechtaluk",
      "state": "MD",
      "district": 6,
      "party": "D",
      "chamber": "house",
      "antiArms": true,
      "ps": "UPCOMING",
      "primaryDate": "2026-06-23",
      "website": "https://www.ethanformd.com/",
      "source": "manual+trackaipac",
      "note": "Endorsed by TrackAIPAC / Citizens Against AIPAC Corruption. Rejects AIPAC contributions.",
      "opponent": "",
      "incumbentParty": ""
    },
    {
      "name": "Jakeya Johnson",
      "state": "MD",
      "district": 4,
      "party": "D",
      "chamber": "house",
      "antiArms": true,
      "ps": "UPCOMING",
      "primaryDate": "2026-06-23",
      "website": "https://jakeyajohnson.com/",
      "source": "manual+trackaipac",
      "note": "Endorsed by TrackAIPAC / Citizens Against AIPAC Corruption. Rejects AIPAC contributions.",
      "opponent": "",
      "incumbentParty": ""
    },
    {
      "name": "Mark Conway",
      "state": "MD",
      "district": 7,
      "party": "D",
      "chamber": "house",
      "antiArms": true,
      "ps": "UPCOMING",
      "primaryDate": "2026-06-23",
      "website": "https://www.conway4congress.com/",
      "source": "manual+trackaipac",
      "note": "Endorsed by TrackAIPAC / Citizens Against AIPAC Corruption. Rejects AIPAC contributions.",
      "opponent": "",
      "incumbentParty": ""
    },
    {
      "name": "Abdul el-Sayed",
      "state": "MI",
      "district": 11,
      "party": "D",
      "chamber": "house",
      "note": "Former Oakland Co. exec; calls the Gaza campaign genocide; opposes all offensive US arms. Vs. Rep. Haley Stevens.",
      "primaryDate": "2026-08-04",
      "ps": "UPCOMING",
      "opponent": "Haley Stevens (incumbent)",
      "incumbentParty": "D"
    },
    {
      "name": "Aisha Farooqi",
      "state": "MI",
      "district": 11,
      "party": "D",
      "chamber": "house",
      "antiArms": true,
      "ps": "UPCOMING",
      "primaryDate": "2026-08-04",
      "website": "https://aishaforcongress.com/",
      "source": "manual+trackaipac",
      "note": "Endorsed by TrackAIPAC / Citizens Against AIPAC Corruption. Rejects AIPAC contributions.",
      "opponent": "",
      "incumbentParty": ""
    },
    {
      "name": "Donavan McKinney",
      "state": "MI",
      "district": 13,
      "party": "D",
      "chamber": "house",
      "antiArms": true,
      "ps": "UPCOMING",
      "primaryDate": "2026-08-04",
      "website": "https://www.donavanforcongress.com/",
      "source": "manual+trackaipac",
      "note": "Endorsed by TrackAIPAC / Citizens Against AIPAC Corruption. Rejects AIPAC contributions.",
      "opponent": "",
      "incumbentParty": ""
    },
    {
      "name": "Kyle Blomquist",
      "state": "MI",
      "district": 1,
      "party": "D",
      "chamber": "house",
      "antiArms": true,
      "ps": "UPCOMING",
      "primaryDate": "2026-08-04",
      "website": "https://www.blomquistforcongress.com/",
      "source": "manual+trackaipac",
      "note": "Endorsed by TrackAIPAC / Citizens Against AIPAC Corruption. Rejects AIPAC contributions.",
      "opponent": "",
      "incumbentParty": ""
    },
    {
      "name": "William Lawrence",
      "state": "MI",
      "district": 7,
      "party": "D",
      "chamber": "house",
      "antiArms": true,
      "ps": "UPCOMING",
      "primaryDate": "2026-08-04",
      "website": "https://wewill2026.com/",
      "source": "manual+trackaipac",
      "note": "Endorsed by TrackAIPAC / Citizens Against AIPAC Corruption. Rejects AIPAC contributions.",
      "opponent": "",
      "incumbentParty": ""
    },
    {
      "name": "Cori Bush",
      "state": "MO",
      "district": 1,
      "party": "D",
      "chamber": "house",
      "note": "Defeated Aug 2024 \u2014 AIPAC spent $8.5M. 2026 comeback filed vs. Wesley Bell. Endorsed by DSA and Tlaib.",
      "primaryDate": "2026-08-04",
      "ps": "UPCOMING",
      "opponent": "Wesley Bell (incumbent)",
      "incumbentParty": "D",
      "website": "https://www.coribush.org/",
      "source": "manual+trackaipac",
      "antiArms": true
    },
    {
      "name": "Hartzell Gray",
      "state": "MO",
      "district": 4,
      "party": "D",
      "chamber": "house",
      "antiArms": true,
      "ps": "UPCOMING",
      "primaryDate": "2026-08-04",
      "website": "https://www.hartzellforcongress.com/",
      "source": "manual+trackaipac",
      "note": "Endorsed by TrackAIPAC / Citizens Against AIPAC Corruption. Rejects AIPAC contributions.",
      "opponent": "",
      "incumbentParty": ""
    },
    {
      "name": "Ashley Bell",
      "state": "NC",
      "district": 10,
      "party": "D",
      "chamber": "house",
      "antiArms": true,
      "ps": "GENERAL",
      "primaryDate": "2026-11-03",
      "website": "https://www.ashleybellforcongress.com/",
      "source": "manual+trackaipac",
      "note": "Endorsed by TrackAIPAC / Citizens Against AIPAC Corruption. Rejects AIPAC contributions.",
      "opponent": "",
      "incumbentParty": ""
    },
    {
      "name": "Nida Allam",
      "state": "NC",
      "district": 4,
      "party": "D",
      "chamber": "house",
      "note": "Durham Co. Commissioner; endorsed by Bernie Sanders. Foushee leads 49.18% vs 48.22% \u2014 margin of 1,202 votes. Allam confirmed recount request. $4.5M outside spending set NC primary record.",
      "primaryDate": "2026-03-03",
      "ps": "RECOUNT",
      "opponent": "Valerie Foushee (incumbent)",
      "incumbentParty": "D"
    },
    {
      "name": "Heath Howard",
      "state": "NH",
      "district": 1,
      "party": "D",
      "chamber": "house",
      "antiArms": true,
      "ps": "UPCOMING",
      "primaryDate": "2026-09-08",
      "website": "https://www.heathhowardnh.com/",
      "source": "manual+trackaipac",
      "note": "Endorsed by TrackAIPAC / Citizens Against AIPAC Corruption. Rejects AIPAC contributions.",
      "opponent": "",
      "incumbentParty": ""
    },
    {
      "name": "Paige Beauchemin",
      "state": "NH",
      "district": 2,
      "party": "D",
      "chamber": "house",
      "antiArms": true,
      "ps": "UPCOMING",
      "primaryDate": "2026-09-08",
      "website": "https://www.paigefornh.com/",
      "source": "manual+trackaipac",
      "note": "Endorsed by TrackAIPAC / Citizens Against AIPAC Corruption. Rejects AIPAC contributions.",
      "opponent": "",
      "incumbentParty": "",
      "fec_id": "H6NH02261"
    },
    {
      "name": "Adam Hamawy",
      "state": "NJ",
      "district": 12,
      "party": "D",
      "chamber": "house",
      "antiArms": true,
      "antiArmsLevel": "yes",
      "ps": "UPCOMING",
      "primaryDate": "2026-06-02",
      "website": "https://hamawyfornj.com/",
      "source": "trackaipac",
      "note": "Endorsed by Citizens Against AIPAC Corruption.",
      "opponent": "",
      "incumbentParty": ""
    },
    {
      "name": "Analilia Mejia",
      "state": "NJ",
      "district": 11,
      "party": "D",
      "chamber": "house",
      "antiArms": true,
      "ps": "GENERAL",
      "primaryDate": "2026-04-16",
      "website": "https://www.analiliafornj.com/",
      "source": "manual+trackaipac",
      "note": "Endorsed by TrackAIPAC / Citizens Against AIPAC Corruption. Rejects AIPAC contributions.",
      "opponent": "",
      "incumbentParty": ""
    },
    {
      "name": "John Hsu",
      "state": "NJ",
      "district": 6,
      "party": "D",
      "chamber": "house",
      "antiArms": true,
      "ps": "UPCOMING",
      "primaryDate": "2026-06-02",
      "website": "https://www.johnhsuforcongress.com/",
      "source": "manual+trackaipac",
      "note": "Endorsed by TrackAIPAC / Citizens Against AIPAC Corruption. Rejects AIPAC contributions.",
      "opponent": "",
      "incumbentParty": ""
    },
    {
      "name": "Katie Bansil",
      "state": "NJ",
      "district": 6,
      "party": "D",
      "chamber": "house",
      "antiArms": true,
      "ps": "UPCOMING",
      "primaryDate": "2026-06-02",
      "website": "https://www.katiebansil.com/",
      "source": "manual+trackaipac",
      "note": "Endorsed by TrackAIPAC / Citizens Against AIPAC Corruption. Rejects AIPAC contributions.",
      "opponent": "",
      "incumbentParty": "",
      "fec_id": "H6NJ06260"
    },
    {
      "name": "Mussab Ali",
      "state": "NJ",
      "district": 8,
      "party": "D",
      "chamber": "house",
      "antiArms": true,
      "ps": "UPCOMING",
      "primaryDate": "2026-06-02",
      "website": "https://www.alifornj.com/",
      "source": "manual+trackaipac",
      "note": "Endorsed by TrackAIPAC / Citizens Against AIPAC Corruption. Rejects AIPAC contributions.",
      "opponent": "",
      "incumbentParty": ""
    },
    {
      "name": "James Lally",
      "state": "NV",
      "district": 3,
      "party": "D",
      "chamber": "house",
      "antiArms": true,
      "ps": "UPCOMING",
      "primaryDate": "2026-06-09",
      "website": "https://lallyfornv.com/",
      "source": "manual+trackaipac",
      "note": "Endorsed by TrackAIPAC / Citizens Against AIPAC Corruption. Rejects AIPAC contributions.",
      "opponent": "",
      "incumbentParty": ""
    },
    {
      "name": "Morgan Wadsworth",
      "state": "NV",
      "district": 2,
      "party": "D",
      "chamber": "house",
      "antiArms": true,
      "antiArmsLevel": "yes",
      "ps": "UPCOMING",
      "primaryDate": "2026-06-09",
      "website": "https://www.wadsworthfornevada.com/",
      "source": "trackaipac",
      "note": "Endorsed by Citizens Against AIPAC Corruption.",
      "opponent": "",
      "incumbentParty": ""
    },
    {
      "name": "Chuck Park",
      "state": "NY",
      "district": 6,
      "party": "D",
      "chamber": "house",
      "antiArms": true,
      "ps": "UPCOMING",
      "primaryDate": "2026-06-23",
      "website": "https://chuckforqueens.com/",
      "source": "manual+trackaipac",
      "note": "Endorsed by TrackAIPAC / Citizens Against AIPAC Corruption. Rejects AIPAC contributions.",
      "opponent": "",
      "incumbentParty": ""
    },
    {
      "name": "Claire Valdez",
      "state": "NY",
      "district": 7,
      "party": "D",
      "chamber": "house",
      "antiArms": true,
      "ps": "UPCOMING",
      "primaryDate": "2026-06-23",
      "website": "https://clairevaldezforcongress.com/",
      "source": "manual+trackaipac",
      "note": "Endorsed by TrackAIPAC / Citizens Against AIPAC Corruption. Rejects AIPAC contributions.",
      "opponent": "",
      "incumbentParty": ""
    },
    {
      "name": "Darializa Avila Chevalier",
      "state": "NY",
      "district": 13,
      "party": "D",
      "chamber": "house",
      "antiArms": true,
      "ps": "UPCOMING",
      "primaryDate": "2026-06-23",
      "website": "https://www.darializaforcongress.com/",
      "source": "manual+trackaipac",
      "note": "Endorsed by TrackAIPAC / Citizens Against AIPAC Corruption. Rejects AIPAC contributions.",
      "opponent": "",
      "incumbentParty": "",
      "fec_id": "H6NY13279"
    },
    {
      "name": "Effie Phillips-Staley",
      "state": "NY",
      "district": 17,
      "party": "D",
      "chamber": "house",
      "antiArms": true,
      "antiArmsLevel": "yes",
      "ps": "UPCOMING",
      "primaryDate": "2026-06-23",
      "website": "https://effieforcongress.com/",
      "source": "trackaipac",
      "note": "Endorsed by Citizens Against AIPAC Corruption.",
      "opponent": "",
      "incumbentParty": ""
    },
    {
      "name": "Karen Ortiz",
      "state": "NY",
      "district": 12,
      "party": "I",
      "chamber": "house",
      "antiArms": true,
      "antiArmsLevel": "yes",
      "ps": "GENERAL",
      "primaryDate": "2026-11-03",
      "website": "https://ko4congress.com/",
      "source": "trackaipac",
      "note": "Endorsed by Citizens Against AIPAC Corruption.",
      "opponent": "",
      "incumbentParty": ""
    },
    {
      "name": "Larry Sharpe",
      "state": "NY",
      "district": null,
      "party": "R",
      "chamber": "house",
      "antiArms": true,
      "antiArmsLevel": "yes",
      "ps": "UPCOMING",
      "primaryDate": "",
      "website": "",
      "source": "rlc_endorsed",
      "note": "Endorsed by Republican Liberty Caucus for Governor of New York\u201d\" loading=\"lazy\">",
      "opponent": "",
      "incumbentParty": ""
    },
    {
      "name": "Michael Blake",
      "state": "NY",
      "district": 15,
      "party": "D",
      "chamber": "house",
      "antiArms": true,
      "antiArmsLevel": "yes",
      "ps": "UPCOMING",
      "primaryDate": "2026-06-23",
      "website": "https://www.michaelblakeforcongress.com/",
      "source": "trackaipac",
      "note": "Endorsed by Citizens Against AIPAC Corruption.",
      "opponent": "",
      "incumbentParty": ""
    },
    {
      "name": "Salvatore Padellaro",
      "state": "NY",
      "district": 5,
      "party": "D",
      "chamber": "house",
      "antiArms": true,
      "ps": "UPCOMING",
      "primaryDate": "2026-06-23",
      "website": "https://sal4congress.com/",
      "source": "manual+trackaipac",
      "note": "Endorsed by TrackAIPAC / Citizens Against AIPAC Corruption. Rejects AIPAC contributions.",
      "opponent": "",
      "incumbentParty": ""
    },
    {
      "name": "Damon Lynch",
      "state": "OH",
      "district": 1,
      "party": "D",
      "chamber": "house",
      "antiArms": true,
      "antiArmsLevel": "yes",
      "ps": "UPCOMING",
      "primaryDate": "2026-05-05",
      "website": "https://friendsofdamonlynch.com/",
      "source": "trackaipac",
      "note": "Endorsed by Citizens Against AIPAC Corruption.",
      "opponent": "",
      "incumbentParty": ""
    },
    {
      "name": "Jerrad Christian",
      "state": "OH",
      "district": 12,
      "party": "D",
      "chamber": "house",
      "antiArms": true,
      "ps": "UPCOMING",
      "primaryDate": "2026-05-05",
      "website": "https://www.christianforohio.com/",
      "source": "manual+trackaipac",
      "note": "Endorsed by TrackAIPAC / Citizens Against AIPAC Corruption. Rejects AIPAC contributions.",
      "opponent": "",
      "incumbentParty": ""
    },
    {
      "name": "Jessica Salas",
      "state": "OR",
      "district": 3,
      "party": "D",
      "chamber": "house",
      "antiArms": true,
      "ps": "UPCOMING",
      "primaryDate": "2026-05-19",
      "website": "https://www.jsalfororegon.com/",
      "source": "manual+trackaipac",
      "note": "Endorsed by TrackAIPAC / Citizens Against AIPAC Corruption. Rejects AIPAC contributions.",
      "opponent": "",
      "incumbentParty": ""
    },
    {
      "name": "Melissa Bird",
      "state": "OR",
      "district": 4,
      "party": "D",
      "chamber": "house",
      "antiArms": true,
      "antiArmsLevel": "yes",
      "ps": "UPCOMING",
      "primaryDate": "2026-05-19",
      "website": "https://www.melissabirdforcongress.com/",
      "source": "trackaipac",
      "note": "Endorsed by Citizens Against AIPAC Corruption.",
      "opponent": "",
      "incumbentParty": ""
    },
    {
      "name": "Zeva Rosenbaum",
      "state": "OR",
      "district": 5,
      "party": "D",
      "chamber": "house",
      "antiArms": true,
      "antiArmsLevel": "yes",
      "ps": "UPCOMING",
      "primaryDate": "2026-05-19",
      "website": "https://www.zevaforcongress.com/",
      "source": "trackaipac",
      "note": "Endorsed by Citizens Against AIPAC Corruption.",
      "opponent": "",
      "incumbentParty": ""
    },
    {
      "name": "Chris Rabb",
      "state": "PA",
      "district": 3,
      "party": "D",
      "chamber": "house",
      "antiArms": true,
      "antiArmsLevel": "yes",
      "ps": "UPCOMING",
      "primaryDate": "2026-05-19",
      "website": "https://www.chrisrabb.com/",
      "source": "trackaipac",
      "note": "Endorsed by Citizens Against AIPAC Corruption.",
      "opponent": "",
      "incumbentParty": ""
    },
    {
      "name": "Lucia Simonelli",
      "state": "PA",
      "district": 1,
      "party": "D",
      "chamber": "house",
      "antiArms": true,
      "antiArmsLevel": "yes",
      "ps": "UPCOMING",
      "primaryDate": "2026-05-19",
      "website": "https://www.luciaforcongress.com/",
      "source": "trackaipac",
      "note": "Endorsed by Citizens Against AIPAC Corruption.",
      "opponent": "",
      "incumbentParty": ""
    },
    {
      "name": "Justin J. Pearson",
      "state": "TN",
      "district": 9,
      "party": "D",
      "chamber": "house",
      "antiArms": true,
      "antiArmsLevel": "yes",
      "ps": "UPCOMING",
      "primaryDate": "2026-08-06",
      "website": "https://www.votejustinj.com/",
      "source": "trackaipac",
      "note": "Endorsed by Citizens Against AIPAC Corruption.",
      "opponent": "",
      "incumbentParty": ""
    },
    {
      "name": "Brandon Herrera",
      "state": "TX",
      "district": 23,
      "party": "R",
      "chamber": "house",
      "note": "Firearms YouTuber and gunsmith; ran vs. pro-Israel Rep. Tony Gonzales on opposition to open-ended foreign military aid. Forced runoff Mar 3.",
      "primaryDate": "2026-03-03",
      "ps": "RUNOFF",
      "opponent": "Tony Gonzales",
      "incumbentParty": "R"
    },
    {
      "name": "Frederick Haynes III",
      "state": "TX",
      "district": 30,
      "party": "D",
      "chamber": "house",
      "note": "Won Mar 3 primary with ~74% of the vote. Dallas pastor; endorsed by Crockett; calls for ceasefire and end to offensive US arms to Israel. Heavily favored in general (D+25 district).",
      "primaryDate": "2026-03-03",
      "ps": "WON",
      "opponent": "Crockett open seat",
      "incumbentParty": "D",
      "website": "https://www.haynesforcongress.com/",
      "source": "manual+trackaipac",
      "antiArms": true
    },
    {
      "name": "James Talarico",
      "state": "TX",
      "district": null,
      "party": "D",
      "chamber": "senate",
      "note": "TX state Rep. Won Democratic Senate primary Mar 3, 2026. Pledged to ban offensive arms sales to Israel. Faces Cornyn or Paxton in November.",
      "primaryDate": "2026-03-03",
      "ps": "WON",
      "opponent": "Jasmine Crockett (primary)",
      "incumbentParty": "R"
    },
    {
      "name": "Kyle Rable",
      "state": "TX",
      "district": 19,
      "party": "D",
      "chamber": "house",
      "antiArms": true,
      "antiArmsLevel": "yes",
      "ps": "GENERAL",
      "primaryDate": "2026-11-03",
      "website": "https://www.rableforwesttexas.com/",
      "source": "trackaipac",
      "note": "Endorsed by Citizens Against AIPAC Corruption.",
      "opponent": "",
      "incumbentParty": ""
    },
    {
      "name": "Maureen Galindo",
      "state": "TX",
      "district": 35,
      "party": "D",
      "chamber": "house",
      "antiArms": true,
      "ps": "UPCOMING",
      "primaryDate": "2026-05-26",
      "website": "https://www.maureenforuscongress.com/",
      "source": "manual+trackaipac",
      "note": "Endorsed by TrackAIPAC / Citizens Against AIPAC Corruption. Rejects AIPAC contributions.",
      "opponent": "",
      "incumbentParty": ""
    },
    {
      "name": "Tanya Lloyd",
      "state": "TX",
      "district": 27,
      "party": "D",
      "chamber": "house",
      "antiArms": true,
      "ps": "GENERAL",
      "primaryDate": "2026-11-03",
      "website": "https://www.tanyafortexas.com/",
      "source": "manual+trackaipac",
      "note": "Endorsed by TrackAIPAC / Citizens Against AIPAC Corruption. Rejects AIPAC contributions.",
      "opponent": "",
      "incumbentParty": ""
    },
    {
      "name": "Zeeshan Hafeez",
      "state": "TX",
      "district": 33,
      "party": "D",
      "chamber": "house",
      "note": "Georgetown Law/UVA MBA; no corporate PAC money; calls for end to US arms sales to Israel. Running in 4-way primary vs. incumbent Julie Johnson and former Rep. Colin Allred. Results pending Mar 3.",
      "primaryDate": "2026-03-03",
      "ps": "RESULTS_PENDING",
      "opponent": "Julie Johnson (incumbent)",
      "incumbentParty": "D"
    },
    {
      "name": "Nate Blouin",
      "state": "UT",
      "district": 1,
      "party": "D",
      "chamber": "house",
      "antiArms": true,
      "ps": "UPCOMING",
      "primaryDate": "2026-06-23",
      "website": "https://www.nateforutah.com/",
      "source": "manual+trackaipac",
      "note": "Endorsed by TrackAIPAC / Citizens Against AIPAC Corruption. Rejects AIPAC contributions.",
      "opponent": "",
      "incumbentParty": ""
    },
    {
      "name": "Alex Mooney",
      "state": "VA",
      "district": null,
      "party": "R",
      "chamber": "senate",
      "antiArms": true,
      "antiArmsLevel": "soft",
      "ps": "UPCOMING",
      "primaryDate": "",
      "website": "",
      "source": "rlc_endorsed",
      "note": "Endorsed by Republican Liberty Caucus for U.S. Senate in West Virginia\" >",
      "opponent": "",
      "incumbentParty": ""
    },
    {
      "name": "Mo Seifeldein",
      "state": "VA",
      "district": 8,
      "party": "D",
      "chamber": "house",
      "antiArms": true,
      "ps": "UPCOMING",
      "primaryDate": "2026-06-16",
      "website": "https://moforcongress.com/",
      "source": "manual+trackaipac",
      "note": "Endorsed by TrackAIPAC / Citizens Against AIPAC Corruption. Rejects AIPAC contributions.",
      "opponent": "",
      "incumbentParty": ""
    },
    {
      "name": "Salaam Bhatti",
      "state": "VA",
      "district": 1,
      "party": "D",
      "chamber": "house",
      "antiArms": true,
      "ps": "UPCOMING",
      "primaryDate": "2026-06-16",
      "website": "https://salaamforva.com/",
      "source": "manual+trackaipac",
      "note": "Endorsed by TrackAIPAC / Citizens Against AIPAC Corruption. Rejects AIPAC contributions.",
      "opponent": "",
      "incumbentParty": ""
    },
    {
      "name": "Brent Hennrich",
      "state": "WA",
      "district": 3,
      "party": "D",
      "chamber": "house",
      "antiArms": true,
      "ps": "UPCOMING",
      "primaryDate": "2026-08-04",
      "website": "https://brenthennrich.com/",
      "source": "manual+trackaipac",
      "note": "Endorsed by TrackAIPAC / Citizens Against AIPAC Corruption. Rejects AIPAC contributions.",
      "opponent": "",
      "incumbentParty": ""
    },
    {
      "name": "Kshama Sawant",
      "state": "WA",
      "district": 9,
      "party": "I",
      "chamber": "house",
      "antiArms": true,
      "ps": "UPCOMING",
      "primaryDate": "2026-08-04",
      "website": "https://www.kshamasawant.org/",
      "source": "manual+trackaipac",
      "note": "Endorsed by TrackAIPAC / Citizens Against AIPAC Corruption. Rejects AIPAC contributions.",
      "opponent": "",
      "incumbentParty": ""
    },
    {
      "name": "Aaron Wojciechowski",
      "state": "WI",
      "district": 6,
      "party": "D",
      "chamber": "house",
      "antiArms": true,
      "ps": "UPCOMING",
      "primaryDate": "2026-08-11",
      "website": "https://www.wojoforcongress.com/",
      "source": "manual+trackaipac",
      "note": "Endorsed by TrackAIPAC / Citizens Against AIPAC Corruption. Rejects AIPAC contributions.",
      "opponent": "",
      "incumbentParty": ""
    },
    {
      "name": "Brit Aguirre",
      "state": "WV",
      "district": 1,
      "party": "D",
      "chamber": "house",
      "antiArms": true,
      "ps": "UPCOMING",
      "primaryDate": "2026-05-12",
      "website": "https://britforwv.com/",
      "source": "manual+trackaipac",
      "note": "Endorsed by TrackAIPAC / Citizens Against AIPAC Corruption. Rejects AIPAC contributions.",
      "opponent": "",
      "incumbentParty": ""
    }
  ]
}